{
  "Constituency": {
    "countInfo": {
      "Constituency_Name": "Queen's University of Belfast",
      "Constituency_Number": "",
      "Number_Of_Seats": "4",
      "Spoiled": "",
      "Total_Electorate": "",
      "Total_Poll": "",
      "Valid_Poll": ""
    },
    "countGroup": [
      {
        "Candidate_First_Pref_Votes": "608.00",
        "Candidate_Id": "14753711",
        "Constituency_Number": "",
        "Count_Number": "1",
        "Firstname": "Robert",
        "Occurred_On_Count": "",
        "Party_Colour": "#48A5EE",
        "Party_Name": "Ulster Unionist Party",
        "Status": "Elected",
        "Surname": "Corkey",
        "Total_Votes": "608.00",
        "Transfers": "0.00",
        "candidateName": "Robert Corkey",
        "id": 0
      },
      {
        "Candidate_First_Pref_Votes": "600.00",
        "Candidate_Id": "13373142",
        "Constituency_Number": "",
        "Count_Number": "1",
        "Firstname": "Robert James",
        "Occurred_On_Count": "",
        "Party_Colour": "#48A5EE",
        "Party_Name": "Ulster Unionist Party",
        "Status": "Elected",
        "Surname": "Johnstone",
        "Total_Votes": "600.00",
        "Transfers": "0.00",
        "candidateName": "Robert James Johnstone",
        "id": 1
      },
      {
        "Candidate_First_Pref_Votes": "369.00",
        "Candidate_Id": "905270",
        "Constituency_Number": "",
        "Count_Number": "1",
        "Firstname": "Arthur Brownlow",
        "Occurred_On_Count": "",
        "Party_Colour": "#48A5EE",
        "Party_Name": "Ulster Unionist Party",
        "Status": "Elected",
        "Surname": "Mitchell",
        "Total_Votes": "369.00",
        "Transfers": "0.00",
        "candidateName": "Arthur Brownlow Mitchell",
        "id": 2
      },
      {
        "Candidate_First_Pref_Votes": "359.00",
        "Candidate_Id": "13336879",
        "Constituency_Number": "",
        "Count_Number": "1",
        "Firstname": "Frederick",
        "Occurred_On_Count": "",
        "Party_Colour": "#DCDCDC",
        "Party_Name": "Independent",
        "Status": "Elected",
        "Surname": "McSorley",
        "Total_Votes": "359.00",
        "Transfers": "0.00",
        "candidateName": "Frederick McSorley",
        "id": 3
      },
      {
        "Candidate_First_Pref_Votes": "259.00",
        "Candidate_Id": "477573",
        "Constituency_Number": "",
        "Count_Number": "1",
        "Firstname": "S.",
        "Occurred_On_Count": "",
        "Party_Colour": "#AADFFF",
        "Party_Name": "Independent Unionist",
        "Status": "",
        "Surname": "Sims",
        "Total_Votes": "259.00",
        "Transfers": "0.00",
        "candidateName": "S. Sims",
        "id": 4
      },
      {
        "Candidate_First_Pref_Votes": "253.00",
        "Candidate_Id": "7843025",
        "Constituency_Number": "",
        "Count_Number": "1",
        "Firstname": "John",
        "Occurred_On_Count": "",
        "Party_Colour": "#48A5EE",
        "Party_Name": "Ulster Unionist Party",
        "Status": "",
        "Surname": "MacDermott",
        "Total_Votes": "253.00",
        "Transfers": "0.00",
        "candidateName": "John MacDermott",
        "id": 5
      }
    ]
  }
}