{
  "Constituency": {
    "countInfo": {
      "Constituency_Name": "Enniskillen",
      "Constituency_Number": "",
      "Number_Of_Seats": "6",
      "Quota": "1097",
      "Total_Electorate": "13642",
      "Total_Poll": "7775",
      "Valid_Poll": "7676",
      "Spoiled": "99",
      "Council_Name": "Fermanagh and Omagh",
      "DEA_Vintage_Year": "2014"
    },
    "countGroup": [
      {
        "Constituency_Number": "",
        "Candidate_Id": "1888962948",
        "Count_Number": "1",
        "Firstname": "Keith",
        "Surname": "Elliott",
        "Candidate_First_Pref_Votes": "1029.00",
        "Transfers": "0.00",
        "Total_Votes": "1029.00",
        "Status": "Elected",
        "Occurred_On_Count": "10",
        "Party_Name": "DUP",
        "Deduplicated Party Name": "DUP",
        "Wikipedia Party Name": "DUP",
        "Party_Colour": "#D46A4C",
        "candidateName": "Keith Elliott",
        "id": 0
      },
      {
        "Constituency_Number": "",
        "Candidate_Id": "1888962948",
        "Count_Number": "2",
        "Firstname": "Keith",
        "Surname": "Elliott",
        "Candidate_First_Pref_Votes": "1029.00",
        "Transfers": "383.00",
        "Total_Votes": "1412.00",
        "Status": "Elected",
        "Occurred_On_Count": "10",
        "Party_Name": "DUP",
        "Deduplicated Party Name": "DUP",
        "Wikipedia Party Name": "DUP",
        "Party_Colour": "#D46A4C",
        "candidateName": "Keith Elliott",
        "id": 1
      },
      {
        "Constituency_Number": "",
        "Candidate_Id": "1888962948",
        "Count_Number": "3",
        "Firstname": "Keith",
        "Surname": "Elliott",
        "Candidate_First_Pref_Votes": "1029.00",
        "Transfers": "-315.00",
        "Total_Votes": "1097.00",
        "Status": "Elected",
        "Occurred_On_Count": "10",
        "Party_Name": "DUP",
        "Deduplicated Party Name": "DUP",
        "Wikipedia Party Name": "DUP",
        "Party_Colour": "#D46A4C",
        "candidateName": "Keith Elliott",
        "id": 2
      },
      {
        "Constituency_Number": "",
        "Candidate_Id": "1888962948",
        "Count_Number": "4",
        "Firstname": "Keith",
        "Surname": "Elliott",
        "Candidate_First_Pref_Votes": "1029.00",
        "Transfers": "0.00",
        "Total_Votes": "1097.00",
        "Status": "Elected",
        "Occurred_On_Count": "10",
        "Party_Name": "DUP",
        "Deduplicated Party Name": "DUP",
        "Wikipedia Party Name": "DUP",
        "Party_Colour": "#D46A4C",
        "candidateName": "Keith Elliott",
        "id": 3
      },
      {
        "Constituency_Number": "",
        "Candidate_Id": "1888962948",
        "Count_Number": "5",
        "Firstname": "Keith",
        "Surname": "Elliott",
        "Candidate_First_Pref_Votes": "1029.00",
        "Transfers": "0.00",
        "Total_Votes": "1097.00",
        "Status": "Elected",
        "Occurred_On_Count": "10",
        "Party_Name": "DUP",
        "Deduplicated Party Name": "DUP",
        "Wikipedia Party Name": "DUP",
        "Party_Colour": "#D46A4C",
        "candidateName": "Keith Elliott",
        "id": 4
      },
      {
        "Constituency_Number": "",
        "Candidate_Id": "1888962948",
        "Count_Number": "6",
        "Firstname": "Keith",
        "Surname": "Elliott",
        "Candidate_First_Pref_Votes": "1029.00",
        "Transfers": "0.00",
        "Total_Votes": "1097.00",
        "Status": "Elected",
        "Occurred_On_Count": "10",
        "Party_Name": "DUP",
        "Deduplicated Party Name": "DUP",
        "Wikipedia Party Name": "DUP",
        "Party_Colour": "#D46A4C",
        "candidateName": "Keith Elliott",
        "id": 5
      },
      {
        "Constituency_Number": "",
        "Candidate_Id": "1888962948",
        "Count_Number": "7",
        "Firstname": "Keith",
        "Surname": "Elliott",
        "Candidate_First_Pref_Votes": "1029.00",
        "Transfers": "0.00",
        "Total_Votes": "1097.00",
        "Status": "Elected",
        "Occurred_On_Count": "10",
        "Party_Name": "DUP",
        "Deduplicated Party Name": "DUP",
        "Wikipedia Party Name": "DUP",
        "Party_Colour": "#D46A4C",
        "candidateName": "Keith Elliott",
        "id": 6
      },
      {
        "Constituency_Number": "",
        "Candidate_Id": "1888962948",
        "Count_Number": "8",
        "Firstname": "Keith",
        "Surname": "Elliott",
        "Candidate_First_Pref_Votes": "1029.00",
        "Transfers": "0.00",
        "Total_Votes": "1097.00",
        "Status": "Elected",
        "Occurred_On_Count": "10",
        "Party_Name": "DUP",
        "Deduplicated Party Name": "DUP",
        "Wikipedia Party Name": "DUP",
        "Party_Colour": "#D46A4C",
        "candidateName": "Keith Elliott",
        "id": 7
      },
      {
        "Constituency_Number": "",
        "Candidate_Id": "1888962948",
        "Count_Number": "9",
        "Firstname": "Keith",
        "Surname": "Elliott",
        "Candidate_First_Pref_Votes": "1029.00",
        "Transfers": "0.00",
        "Total_Votes": "1097.00",
        "Status": "Elected",
        "Occurred_On_Count": "10",
        "Party_Name": "DUP",
        "Deduplicated Party Name": "DUP",
        "Wikipedia Party Name": "DUP",
        "Party_Colour": "#D46A4C",
        "candidateName": "Keith Elliott",
        "id": 8
      },
      {
        "Constituency_Number": "",
        "Candidate_Id": "1888962948",
        "Count_Number": "10",
        "Firstname": "Keith",
        "Surname": "Elliott",
        "Candidate_First_Pref_Votes": "1029.00",
        "Transfers": "0.00",
        "Total_Votes": "1097.00",
        "Status": "Elected",
        "Occurred_On_Count": "10",
        "Party_Name": "DUP",
        "Deduplicated Party Name": "DUP",
        "Wikipedia Party Name": "DUP",
        "Party_Colour": "#D46A4C",
        "candidateName": "Keith Elliott",
        "id": 9
      },
      {
        "Constituency_Number": "",
        "Candidate_Id": "1831073976",
        "Count_Number": "1",
        "Firstname": "Eddie",
        "Surname": "Roofe",
        "Candidate_First_Pref_Votes": "779.00",
        "Transfers": "0.00",
        "Total_Votes": "779.00",
        "Status": "Elected",
        "Occurred_On_Count": "10",
        "Party_Name": "Alliance",
        "Deduplicated Party Name": "Alliance",
        "Wikipedia Party Name": "Alliance",
        "Party_Colour": "#F6CB2F",
        "candidateName": "Eddie Roofe",
        "id": 10
      },
      {
        "Constituency_Number": "",
        "Candidate_Id": "1831073976",
        "Count_Number": "2",
        "Firstname": "Eddie",
        "Surname": "Roofe",
        "Candidate_First_Pref_Votes": "779.00",
        "Transfers": "4.00",
        "Total_Votes": "783.00",
        "Status": "Elected",
        "Occurred_On_Count": "10",
        "Party_Name": "Alliance",
        "Deduplicated Party Name": "Alliance",
        "Wikipedia Party Name": "Alliance",
        "Party_Colour": "#F6CB2F",
        "candidateName": "Eddie Roofe",
        "id": 11
      },
      {
        "Constituency_Number": "",
        "Candidate_Id": "1831073976",
        "Count_Number": "3",
        "Firstname": "Eddie",
        "Surname": "Roofe",
        "Candidate_First_Pref_Votes": "779.00",
        "Transfers": "6.80",
        "Total_Votes": "789.00",
        "Status": "Elected",
        "Occurred_On_Count": "10",
        "Party_Name": "Alliance",
        "Deduplicated Party Name": "Alliance",
        "Wikipedia Party Name": "Alliance",
        "Party_Colour": "#F6CB2F",
        "candidateName": "Eddie Roofe",
        "id": 12
      },
      {
        "Constituency_Number": "",
        "Candidate_Id": "1831073976",
        "Count_Number": "4",
        "Firstname": "Eddie",
        "Surname": "Roofe",
        "Candidate_First_Pref_Votes": "779.00",
        "Transfers": "164.00",
        "Total_Votes": "953.00",
        "Status": "Elected",
        "Occurred_On_Count": "10",
        "Party_Name": "Alliance",
        "Deduplicated Party Name": "Alliance",
        "Wikipedia Party Name": "Alliance",
        "Party_Colour": "#F6CB2F",
        "candidateName": "Eddie Roofe",
        "id": 13
      },
      {
        "Constituency_Number": "",
        "Candidate_Id": "1831073976",
        "Count_Number": "5",
        "Firstname": "Eddie",
        "Surname": "Roofe",
        "Candidate_First_Pref_Votes": "779.00",
        "Transfers": "304.00",
        "Total_Votes": "1257.00",
        "Status": "Elected",
        "Occurred_On_Count": "10",
        "Party_Name": "Alliance",
        "Deduplicated Party Name": "Alliance",
        "Wikipedia Party Name": "Alliance",
        "Party_Colour": "#F6CB2F",
        "candidateName": "Eddie Roofe",
        "id": 14
      },
      {
        "Constituency_Number": "",
        "Candidate_Id": "1831073976",
        "Count_Number": "6",
        "Firstname": "Eddie",
        "Surname": "Roofe",
        "Candidate_First_Pref_Votes": "779.00",
        "Transfers": "-160.80",
        "Total_Votes": "1097.00",
        "Status": "Elected",
        "Occurred_On_Count": "10",
        "Party_Name": "Alliance",
        "Deduplicated Party Name": "Alliance",
        "Wikipedia Party Name": "Alliance",
        "Party_Colour": "#F6CB2F",
        "candidateName": "Eddie Roofe",
        "id": 15
      },
      {
        "Constituency_Number": "",
        "Candidate_Id": "1831073976",
        "Count_Number": "7",
        "Firstname": "Eddie",
        "Surname": "Roofe",
        "Candidate_First_Pref_Votes": "779.00",
        "Transfers": "0.00",
        "Total_Votes": "1097.00",
        "Status": "Elected",
        "Occurred_On_Count": "10",
        "Party_Name": "Alliance",
        "Deduplicated Party Name": "Alliance",
        "Wikipedia Party Name": "Alliance",
        "Party_Colour": "#F6CB2F",
        "candidateName": "Eddie Roofe",
        "id": 16
      },
      {
        "Constituency_Number": "",
        "Candidate_Id": "1831073976",
        "Count_Number": "8",
        "Firstname": "Eddie",
        "Surname": "Roofe",
        "Candidate_First_Pref_Votes": "779.00",
        "Transfers": "0.00",
        "Total_Votes": "1097.00",
        "Status": "Elected",
        "Occurred_On_Count": "10",
        "Party_Name": "Alliance",
        "Deduplicated Party Name": "Alliance",
        "Wikipedia Party Name": "Alliance",
        "Party_Colour": "#F6CB2F",
        "candidateName": "Eddie Roofe",
        "id": 17
      },
      {
        "Constituency_Number": "",
        "Candidate_Id": "1831073976",
        "Count_Number": "9",
        "Firstname": "Eddie",
        "Surname": "Roofe",
        "Candidate_First_Pref_Votes": "779.00",
        "Transfers": "0.00",
        "Total_Votes": "1097.00",
        "Status": "Elected",
        "Occurred_On_Count": "10",
        "Party_Name": "Alliance",
        "Deduplicated Party Name": "Alliance",
        "Wikipedia Party Name": "Alliance",
        "Party_Colour": "#F6CB2F",
        "candidateName": "Eddie Roofe",
        "id": 18
      },
      {
        "Constituency_Number": "",
        "Candidate_Id": "1831073976",
        "Count_Number": "10",
        "Firstname": "Eddie",
        "Surname": "Roofe",
        "Candidate_First_Pref_Votes": "779.00",
        "Transfers": "0.00",
        "Total_Votes": "1097.00",
        "Status": "Elected",
        "Occurred_On_Count": "10",
        "Party_Name": "Alliance",
        "Deduplicated Party Name": "Alliance",
        "Wikipedia Party Name": "Alliance",
        "Party_Colour": "#F6CB2F",
        "candidateName": "Eddie Roofe",
        "id": 19
      },
      {
        "Constituency_Number": "",
        "Candidate_Id": "1112413847",
        "Count_Number": "1",
        "Firstname": "Tommy",
        "Surname": "Maguire",
        "Candidate_First_Pref_Votes": "1024.00",
        "Transfers": "0.00",
        "Total_Votes": "1024.00",
        "Status": "Elected",
        "Occurred_On_Count": "10",
        "Party_Name": "Sinn Féin",
        "Deduplicated Party Name": "Sinn Féin",
        "Wikipedia Party Name": "Sinn Féin",
        "Party_Colour": "#326760",
        "candidateName": "Tommy Maguire",
        "id": 20
      },
      {
        "Constituency_Number": "",
        "Candidate_Id": "1112413847",
        "Count_Number": "2",
        "Firstname": "Tommy",
        "Surname": "Maguire",
        "Candidate_First_Pref_Votes": "1024.00",
        "Transfers": "0.00",
        "Total_Votes": "1024.00",
        "Status": "Elected",
        "Occurred_On_Count": "10",
        "Party_Name": "Sinn Féin",
        "Deduplicated Party Name": "Sinn Féin",
        "Wikipedia Party Name": "Sinn Féin",
        "Party_Colour": "#326760",
        "candidateName": "Tommy Maguire",
        "id": 21
      },
      {
        "Constituency_Number": "",
        "Candidate_Id": "1112413847",
        "Count_Number": "3",
        "Firstname": "Tommy",
        "Surname": "Maguire",
        "Candidate_First_Pref_Votes": "1024.00",
        "Transfers": "0.00",
        "Total_Votes": "1024.00",
        "Status": "Elected",
        "Occurred_On_Count": "10",
        "Party_Name": "Sinn Féin",
        "Deduplicated Party Name": "Sinn Féin",
        "Wikipedia Party Name": "Sinn Féin",
        "Party_Colour": "#326760",
        "candidateName": "Tommy Maguire",
        "id": 22
      },
      {
        "Constituency_Number": "",
        "Candidate_Id": "1112413847",
        "Count_Number": "4",
        "Firstname": "Tommy",
        "Surname": "Maguire",
        "Candidate_First_Pref_Votes": "1024.00",
        "Transfers": "67.00",
        "Total_Votes": "1091.00",
        "Status": "Elected",
        "Occurred_On_Count": "10",
        "Party_Name": "Sinn Féin",
        "Deduplicated Party Name": "Sinn Féin",
        "Wikipedia Party Name": "Sinn Féin",
        "Party_Colour": "#326760",
        "candidateName": "Tommy Maguire",
        "id": 23
      },
      {
        "Constituency_Number": "",
        "Candidate_Id": "1112413847",
        "Count_Number": "5",
        "Firstname": "Tommy",
        "Surname": "Maguire",
        "Candidate_First_Pref_Votes": "1024.00",
        "Transfers": "44.00",
        "Total_Votes": "1135.00",
        "Status": "Elected",
        "Occurred_On_Count": "10",
        "Party_Name": "Sinn Féin",
        "Deduplicated Party Name": "Sinn Féin",
        "Wikipedia Party Name": "Sinn Féin",
        "Party_Colour": "#326760",
        "candidateName": "Tommy Maguire",
        "id": 24
      },
      {
        "Constituency_Number": "",
        "Candidate_Id": "1112413847",
        "Count_Number": "6",
        "Firstname": "Tommy",
        "Surname": "Maguire",
        "Candidate_First_Pref_Votes": "1024.00",
        "Transfers": "0.00",
        "Total_Votes": "1135.00",
        "Status": "Elected",
        "Occurred_On_Count": "10",
        "Party_Name": "Sinn Féin",
        "Deduplicated Party Name": "Sinn Féin",
        "Wikipedia Party Name": "Sinn Féin",
        "Party_Colour": "#326760",
        "candidateName": "Tommy Maguire",
        "id": 25
      },
      {
        "Constituency_Number": "",
        "Candidate_Id": "1112413847",
        "Count_Number": "7",
        "Firstname": "Tommy",
        "Surname": "Maguire",
        "Candidate_First_Pref_Votes": "1024.00",
        "Transfers": "-38.00",
        "Total_Votes": "1097.00",
        "Status": "Elected",
        "Occurred_On_Count": "10",
        "Party_Name": "Sinn Féin",
        "Deduplicated Party Name": "Sinn Féin",
        "Wikipedia Party Name": "Sinn Féin",
        "Party_Colour": "#326760",
        "candidateName": "Tommy Maguire",
        "id": 26
      },
      {
        "Constituency_Number": "",
        "Candidate_Id": "1112413847",
        "Count_Number": "8",
        "Firstname": "Tommy",
        "Surname": "Maguire",
        "Candidate_First_Pref_Votes": "1024.00",
        "Transfers": "0.00",
        "Total_Votes": "1097.00",
        "Status": "Elected",
        "Occurred_On_Count": "10",
        "Party_Name": "Sinn Féin",
        "Deduplicated Party Name": "Sinn Féin",
        "Wikipedia Party Name": "Sinn Féin",
        "Party_Colour": "#326760",
        "candidateName": "Tommy Maguire",
        "id": 27
      },
      {
        "Constituency_Number": "",
        "Candidate_Id": "1112413847",
        "Count_Number": "9",
        "Firstname": "Tommy",
        "Surname": "Maguire",
        "Candidate_First_Pref_Votes": "1024.00",
        "Transfers": "0.00",
        "Total_Votes": "1097.00",
        "Status": "Elected",
        "Occurred_On_Count": "10",
        "Party_Name": "Sinn Féin",
        "Deduplicated Party Name": "Sinn Féin",
        "Wikipedia Party Name": "Sinn Féin",
        "Party_Colour": "#326760",
        "candidateName": "Tommy Maguire",
        "id": 28
      },
      {
        "Constituency_Number": "",
        "Candidate_Id": "1112413847",
        "Count_Number": "10",
        "Firstname": "Tommy",
        "Surname": "Maguire",
        "Candidate_First_Pref_Votes": "1024.00",
        "Transfers": "0.00",
        "Total_Votes": "1097.00",
        "Status": "Elected",
        "Occurred_On_Count": "10",
        "Party_Name": "Sinn Féin",
        "Deduplicated Party Name": "Sinn Féin",
        "Wikipedia Party Name": "Sinn Féin",
        "Party_Colour": "#326760",
        "candidateName": "Tommy Maguire",
        "id": 29
      },
      {
        "Constituency_Number": "",
        "Candidate_Id": "865819421",
        "Count_Number": "1",
        "Firstname": "Roy",
        "Surname": "Crawford",
        "Candidate_First_Pref_Votes": "667.00",
        "Transfers": "0.00",
        "Total_Votes": "667.00",
        "Status": "Elected",
        "Occurred_On_Count": "10",
        "Party_Name": "UUP",
        "Deduplicated Party Name": "UUP",
        "Wikipedia Party Name": "UUP",
        "Party_Colour": "#48A5EE",
        "candidateName": "Roy Crawford",
        "id": 30
      },
      {
        "Constituency_Number": "",
        "Candidate_Id": "865819421",
        "Count_Number": "2",
        "Firstname": "Roy",
        "Surname": "Crawford",
        "Candidate_First_Pref_Votes": "667.00",
        "Transfers": "7.00",
        "Total_Votes": "674.00",
        "Status": "Elected",
        "Occurred_On_Count": "10",
        "Party_Name": "UUP",
        "Deduplicated Party Name": "UUP",
        "Wikipedia Party Name": "UUP",
        "Party_Colour": "#48A5EE",
        "candidateName": "Roy Crawford",
        "id": 31
      },
      {
        "Constituency_Number": "",
        "Candidate_Id": "865819421",
        "Count_Number": "3",
        "Firstname": "Roy",
        "Surname": "Crawford",
        "Candidate_First_Pref_Votes": "667.00",
        "Transfers": "78.20",
        "Total_Votes": "752.00",
        "Status": "Elected",
        "Occurred_On_Count": "10",
        "Party_Name": "UUP",
        "Deduplicated Party Name": "UUP",
        "Wikipedia Party Name": "UUP",
        "Party_Colour": "#48A5EE",
        "candidateName": "Roy Crawford",
        "id": 32
      },
      {
        "Constituency_Number": "",
        "Candidate_Id": "865819421",
        "Count_Number": "4",
        "Firstname": "Roy",
        "Surname": "Crawford",
        "Candidate_First_Pref_Votes": "667.00",
        "Transfers": "14.00",
        "Total_Votes": "766.00",
        "Status": "Elected",
        "Occurred_On_Count": "10",
        "Party_Name": "UUP",
        "Deduplicated Party Name": "UUP",
        "Wikipedia Party Name": "UUP",
        "Party_Colour": "#48A5EE",
        "candidateName": "Roy Crawford",
        "id": 33
      },
      {
        "Constituency_Number": "",
        "Candidate_Id": "865819421",
        "Count_Number": "5",
        "Firstname": "Roy",
        "Surname": "Crawford",
        "Candidate_First_Pref_Votes": "667.00",
        "Transfers": "18.00",
        "Total_Votes": "784.00",
        "Status": "Elected",
        "Occurred_On_Count": "10",
        "Party_Name": "UUP",
        "Deduplicated Party Name": "UUP",
        "Wikipedia Party Name": "UUP",
        "Party_Colour": "#48A5EE",
        "candidateName": "Roy Crawford",
        "id": 34
      },
      {
        "Constituency_Number": "",
        "Candidate_Id": "865819421",
        "Count_Number": "6",
        "Firstname": "Roy",
        "Surname": "Crawford",
        "Candidate_First_Pref_Votes": "667.00",
        "Transfers": "25.92",
        "Total_Votes": "810.00",
        "Status": "Elected",
        "Occurred_On_Count": "10",
        "Party_Name": "UUP",
        "Deduplicated Party Name": "UUP",
        "Wikipedia Party Name": "UUP",
        "Party_Colour": "#48A5EE",
        "candidateName": "Roy Crawford",
        "id": 35
      },
      {
        "Constituency_Number": "",
        "Candidate_Id": "865819421",
        "Count_Number": "7",
        "Firstname": "Roy",
        "Surname": "Crawford",
        "Candidate_First_Pref_Votes": "667.00",
        "Transfers": "0.00",
        "Total_Votes": "810.00",
        "Status": "Elected",
        "Occurred_On_Count": "10",
        "Party_Name": "UUP",
        "Deduplicated Party Name": "UUP",
        "Wikipedia Party Name": "UUP",
        "Party_Colour": "#48A5EE",
        "candidateName": "Roy Crawford",
        "id": 36
      },
      {
        "Constituency_Number": "",
        "Candidate_Id": "865819421",
        "Count_Number": "8",
        "Firstname": "Roy",
        "Surname": "Crawford",
        "Candidate_First_Pref_Votes": "667.00",
        "Transfers": "320.31",
        "Total_Votes": "1130.00",
        "Status": "Elected",
        "Occurred_On_Count": "10",
        "Party_Name": "UUP",
        "Deduplicated Party Name": "UUP",
        "Wikipedia Party Name": "UUP",
        "Party_Colour": "#48A5EE",
        "candidateName": "Roy Crawford",
        "id": 37
      },
      {
        "Constituency_Number": "",
        "Candidate_Id": "865819421",
        "Count_Number": "9",
        "Firstname": "Roy",
        "Surname": "Crawford",
        "Candidate_First_Pref_Votes": "667.00",
        "Transfers": "-33.43",
        "Total_Votes": "1097.00",
        "Status": "Elected",
        "Occurred_On_Count": "10",
        "Party_Name": "UUP",
        "Deduplicated Party Name": "UUP",
        "Wikipedia Party Name": "UUP",
        "Party_Colour": "#48A5EE",
        "candidateName": "Roy Crawford",
        "id": 38
      },
      {
        "Constituency_Number": "",
        "Candidate_Id": "865819421",
        "Count_Number": "10",
        "Firstname": "Roy",
        "Surname": "Crawford",
        "Candidate_First_Pref_Votes": "667.00",
        "Transfers": "0.00",
        "Total_Votes": "1097.00",
        "Status": "Elected",
        "Occurred_On_Count": "10",
        "Party_Name": "UUP",
        "Deduplicated Party Name": "UUP",
        "Wikipedia Party Name": "UUP",
        "Party_Colour": "#48A5EE",
        "candidateName": "Roy Crawford",
        "id": 39
      },
      {
        "Constituency_Number": "",
        "Candidate_Id": "483033516",
        "Count_Number": "1",
        "Firstname": "Dermot",
        "Surname": "Browne",
        "Candidate_First_Pref_Votes": "846.00",
        "Transfers": "0.00",
        "Total_Votes": "846.00",
        "Status": "Elected",
        "Occurred_On_Count": "10",
        "Party_Name": "Sinn Féin",
        "Deduplicated Party Name": "Sinn Féin",
        "Wikipedia Party Name": "Sinn Féin",
        "Party_Colour": "#326760",
        "candidateName": "Dermot Browne",
        "id": 40
      },
      {
        "Constituency_Number": "",
        "Candidate_Id": "483033516",
        "Count_Number": "2",
        "Firstname": "Dermot",
        "Surname": "Browne",
        "Candidate_First_Pref_Votes": "846.00",
        "Transfers": "0.00",
        "Total_Votes": "846.00",
        "Status": "Elected",
        "Occurred_On_Count": "10",
        "Party_Name": "Sinn Féin",
        "Deduplicated Party Name": "Sinn Féin",
        "Wikipedia Party Name": "Sinn Féin",
        "Party_Colour": "#326760",
        "candidateName": "Dermot Browne",
        "id": 41
      },
      {
        "Constituency_Number": "",
        "Candidate_Id": "483033516",
        "Count_Number": "3",
        "Firstname": "Dermot",
        "Surname": "Browne",
        "Candidate_First_Pref_Votes": "846.00",
        "Transfers": "0.00",
        "Total_Votes": "846.00",
        "Status": "Elected",
        "Occurred_On_Count": "10",
        "Party_Name": "Sinn Féin",
        "Deduplicated Party Name": "Sinn Féin",
        "Wikipedia Party Name": "Sinn Féin",
        "Party_Colour": "#326760",
        "candidateName": "Dermot Browne",
        "id": 42
      },
      {
        "Constituency_Number": "",
        "Candidate_Id": "483033516",
        "Count_Number": "4",
        "Firstname": "Dermot",
        "Surname": "Browne",
        "Candidate_First_Pref_Votes": "846.00",
        "Transfers": "33.00",
        "Total_Votes": "879.00",
        "Status": "Elected",
        "Occurred_On_Count": "10",
        "Party_Name": "Sinn Féin",
        "Deduplicated Party Name": "Sinn Féin",
        "Wikipedia Party Name": "Sinn Féin",
        "Party_Colour": "#326760",
        "candidateName": "Dermot Browne",
        "id": 43
      },
      {
        "Constituency_Number": "",
        "Candidate_Id": "483033516",
        "Count_Number": "5",
        "Firstname": "Dermot",
        "Surname": "Browne",
        "Candidate_First_Pref_Votes": "846.00",
        "Transfers": "124.00",
        "Total_Votes": "1003.00",
        "Status": "Elected",
        "Occurred_On_Count": "10",
        "Party_Name": "Sinn Féin",
        "Deduplicated Party Name": "Sinn Féin",
        "Wikipedia Party Name": "Sinn Féin",
        "Party_Colour": "#326760",
        "candidateName": "Dermot Browne",
        "id": 44
      },
      {
        "Constituency_Number": "",
        "Candidate_Id": "483033516",
        "Count_Number": "6",
        "Firstname": "Dermot",
        "Surname": "Browne",
        "Candidate_First_Pref_Votes": "846.00",
        "Transfers": "54.72",
        "Total_Votes": "1057.00",
        "Status": "Elected",
        "Occurred_On_Count": "10",
        "Party_Name": "Sinn Féin",
        "Deduplicated Party Name": "Sinn Féin",
        "Wikipedia Party Name": "Sinn Féin",
        "Party_Colour": "#326760",
        "candidateName": "Dermot Browne",
        "id": 45
      },
      {
        "Constituency_Number": "",
        "Candidate_Id": "483033516",
        "Count_Number": "7",
        "Firstname": "Dermot",
        "Surname": "Browne",
        "Candidate_First_Pref_Votes": "846.00",
        "Transfers": "16.49",
        "Total_Votes": "1074.00",
        "Status": "Elected",
        "Occurred_On_Count": "10",
        "Party_Name": "Sinn Féin",
        "Deduplicated Party Name": "Sinn Féin",
        "Wikipedia Party Name": "Sinn Féin",
        "Party_Colour": "#326760",
        "candidateName": "Dermot Browne",
        "id": 46
      },
      {
        "Constituency_Number": "",
        "Candidate_Id": "483033516",
        "Count_Number": "8",
        "Firstname": "Dermot",
        "Surname": "Browne",
        "Candidate_First_Pref_Votes": "846.00",
        "Transfers": "2.96",
        "Total_Votes": "1077.00",
        "Status": "Elected",
        "Occurred_On_Count": "10",
        "Party_Name": "Sinn Féin",
        "Deduplicated Party Name": "Sinn Féin",
        "Wikipedia Party Name": "Sinn Féin",
        "Party_Colour": "#326760",
        "candidateName": "Dermot Browne",
        "id": 47
      },
      {
        "Constituency_Number": "",
        "Candidate_Id": "483033516",
        "Count_Number": "9",
        "Firstname": "Dermot",
        "Surname": "Browne",
        "Candidate_First_Pref_Votes": "846.00",
        "Transfers": "0.00",
        "Total_Votes": "1077.00",
        "Status": "Elected",
        "Occurred_On_Count": "10",
        "Party_Name": "Sinn Féin",
        "Deduplicated Party Name": "Sinn Féin",
        "Wikipedia Party Name": "Sinn Féin",
        "Party_Colour": "#326760",
        "candidateName": "Dermot Browne",
        "id": 48
      },
      {
        "Constituency_Number": "",
        "Candidate_Id": "483033516",
        "Count_Number": "10",
        "Firstname": "Dermot",
        "Surname": "Browne",
        "Candidate_First_Pref_Votes": "846.00",
        "Transfers": "0.00",
        "Total_Votes": "1077.00",
        "Status": "Elected",
        "Occurred_On_Count": "10",
        "Party_Name": "Sinn Féin",
        "Deduplicated Party Name": "Sinn Féin",
        "Wikipedia Party Name": "Sinn Féin",
        "Party_Colour": "#326760",
        "candidateName": "Dermot Browne",
        "id": 49
      },
      {
        "Constituency_Number": "",
        "Candidate_Id": "1877854758",
        "Count_Number": "1",
        "Firstname": "Robert",
        "Surname": "Irvine",
        "Candidate_First_Pref_Votes": "562.00",
        "Transfers": "0.00",
        "Total_Votes": "562.00",
        "Status": "Elected",
        "Occurred_On_Count": "10",
        "Party_Name": "UUP",
        "Deduplicated Party Name": "UUP",
        "Wikipedia Party Name": "UUP",
        "Party_Colour": "#48A5EE",
        "candidateName": "Robert Irvine",
        "id": 50
      },
      {
        "Constituency_Number": "",
        "Candidate_Id": "1877854758",
        "Count_Number": "2",
        "Firstname": "Robert",
        "Surname": "Irvine",
        "Candidate_First_Pref_Votes": "562.00",
        "Transfers": "18.00",
        "Total_Votes": "580.00",
        "Status": "Elected",
        "Occurred_On_Count": "10",
        "Party_Name": "UUP",
        "Deduplicated Party Name": "UUP",
        "Wikipedia Party Name": "UUP",
        "Party_Colour": "#48A5EE",
        "candidateName": "Robert Irvine",
        "id": 51
      },
      {
        "Constituency_Number": "",
        "Candidate_Id": "1877854758",
        "Count_Number": "3",
        "Firstname": "Robert",
        "Surname": "Irvine",
        "Candidate_First_Pref_Votes": "562.00",
        "Transfers": "93.50",
        "Total_Votes": "673.00",
        "Status": "Elected",
        "Occurred_On_Count": "10",
        "Party_Name": "UUP",
        "Deduplicated Party Name": "UUP",
        "Wikipedia Party Name": "UUP",
        "Party_Colour": "#48A5EE",
        "candidateName": "Robert Irvine",
        "id": 52
      },
      {
        "Constituency_Number": "",
        "Candidate_Id": "1877854758",
        "Count_Number": "4",
        "Firstname": "Robert",
        "Surname": "Irvine",
        "Candidate_First_Pref_Votes": "562.00",
        "Transfers": "11.00",
        "Total_Votes": "684.00",
        "Status": "Elected",
        "Occurred_On_Count": "10",
        "Party_Name": "UUP",
        "Deduplicated Party Name": "UUP",
        "Wikipedia Party Name": "UUP",
        "Party_Colour": "#48A5EE",
        "candidateName": "Robert Irvine",
        "id": 53
      },
      {
        "Constituency_Number": "",
        "Candidate_Id": "1877854758",
        "Count_Number": "5",
        "Firstname": "Robert",
        "Surname": "Irvine",
        "Candidate_First_Pref_Votes": "562.00",
        "Transfers": "17.00",
        "Total_Votes": "701.00",
        "Status": "Elected",
        "Occurred_On_Count": "10",
        "Party_Name": "UUP",
        "Deduplicated Party Name": "UUP",
        "Wikipedia Party Name": "UUP",
        "Party_Colour": "#48A5EE",
        "candidateName": "Robert Irvine",
        "id": 54
      },
      {
        "Constituency_Number": "",
        "Candidate_Id": "1877854758",
        "Count_Number": "6",
        "Firstname": "Robert",
        "Surname": "Irvine",
        "Candidate_First_Pref_Votes": "562.00",
        "Transfers": "19.20",
        "Total_Votes": "720.00",
        "Status": "Elected",
        "Occurred_On_Count": "10",
        "Party_Name": "UUP",
        "Deduplicated Party Name": "UUP",
        "Wikipedia Party Name": "UUP",
        "Party_Colour": "#48A5EE",
        "candidateName": "Robert Irvine",
        "id": 55
      },
      {
        "Constituency_Number": "",
        "Candidate_Id": "1877854758",
        "Count_Number": "7",
        "Firstname": "Robert",
        "Surname": "Irvine",
        "Candidate_First_Pref_Votes": "562.00",
        "Transfers": "0.97",
        "Total_Votes": "721.00",
        "Status": "Elected",
        "Occurred_On_Count": "10",
        "Party_Name": "UUP",
        "Deduplicated Party Name": "UUP",
        "Wikipedia Party Name": "UUP",
        "Party_Colour": "#48A5EE",
        "candidateName": "Robert Irvine",
        "id": 56
      },
      {
        "Constituency_Number": "",
        "Candidate_Id": "1877854758",
        "Count_Number": "8",
        "Firstname": "Robert",
        "Surname": "Irvine",
        "Candidate_First_Pref_Votes": "562.00",
        "Transfers": "273.65",
        "Total_Votes": "995.00",
        "Status": "Elected",
        "Occurred_On_Count": "10",
        "Party_Name": "UUP",
        "Deduplicated Party Name": "UUP",
        "Wikipedia Party Name": "UUP",
        "Party_Colour": "#48A5EE",
        "candidateName": "Robert Irvine",
        "id": 57
      },
      {
        "Constituency_Number": "",
        "Candidate_Id": "1877854758",
        "Count_Number": "9",
        "Firstname": "Robert",
        "Surname": "Irvine",
        "Candidate_First_Pref_Votes": "562.00",
        "Transfers": "33.15",
        "Total_Votes": "1028.00",
        "Status": "Elected",
        "Occurred_On_Count": "10",
        "Party_Name": "UUP",
        "Deduplicated Party Name": "UUP",
        "Wikipedia Party Name": "UUP",
        "Party_Colour": "#48A5EE",
        "candidateName": "Robert Irvine",
        "id": 58
      },
      {
        "Constituency_Number": "",
        "Candidate_Id": "1877854758",
        "Count_Number": "10",
        "Firstname": "Robert",
        "Surname": "Irvine",
        "Candidate_First_Pref_Votes": "562.00",
        "Transfers": "0.00",
        "Total_Votes": "1028.00",
        "Status": "Elected",
        "Occurred_On_Count": "10",
        "Party_Name": "UUP",
        "Deduplicated Party Name": "UUP",
        "Wikipedia Party Name": "UUP",
        "Party_Colour": "#48A5EE",
        "candidateName": "Robert Irvine",
        "id": 59
      },
      {
        "Constituency_Number": "",
        "Candidate_Id": "1542672061",
        "Count_Number": "1",
        "Firstname": "Andrea",
        "Surname": "McManus",
        "Candidate_First_Pref_Votes": "780.00",
        "Transfers": "0.00",
        "Total_Votes": "780.00",
        "Status": "Not Elected",
        "Occurred_On_Count": "10",
        "Party_Name": "Sinn Féin",
        "Deduplicated Party Name": "Sinn Féin",
        "Wikipedia Party Name": "Sinn Féin",
        "Party_Colour": "#326760",
        "candidateName": "Andrea McManus",
        "id": 60
      },
      {
        "Constituency_Number": "",
        "Candidate_Id": "1542672061",
        "Count_Number": "2",
        "Firstname": "Andrea",
        "Surname": "McManus",
        "Candidate_First_Pref_Votes": "780.00",
        "Transfers": "0.00",
        "Total_Votes": "780.00",
        "Status": "Not Elected",
        "Occurred_On_Count": "10",
        "Party_Name": "Sinn Féin",
        "Deduplicated Party Name": "Sinn Féin",
        "Wikipedia Party Name": "Sinn Féin",
        "Party_Colour": "#326760",
        "candidateName": "Andrea McManus",
        "id": 61
      },
      {
        "Constituency_Number": "",
        "Candidate_Id": "1542672061",
        "Count_Number": "3",
        "Firstname": "Andrea",
        "Surname": "McManus",
        "Candidate_First_Pref_Votes": "780.00",
        "Transfers": "0.00",
        "Total_Votes": "780.00",
        "Status": "Not Elected",
        "Occurred_On_Count": "10",
        "Party_Name": "Sinn Féin",
        "Deduplicated Party Name": "Sinn Féin",
        "Wikipedia Party Name": "Sinn Féin",
        "Party_Colour": "#326760",
        "candidateName": "Andrea McManus",
        "id": 62
      },
      {
        "Constituency_Number": "",
        "Candidate_Id": "1542672061",
        "Count_Number": "4",
        "Firstname": "Andrea",
        "Surname": "McManus",
        "Candidate_First_Pref_Votes": "780.00",
        "Transfers": "37.00",
        "Total_Votes": "817.00",
        "Status": "Not Elected",
        "Occurred_On_Count": "10",
        "Party_Name": "Sinn Féin",
        "Deduplicated Party Name": "Sinn Féin",
        "Wikipedia Party Name": "Sinn Féin",
        "Party_Colour": "#326760",
        "candidateName": "Andrea McManus",
        "id": 63
      },
      {
        "Constituency_Number": "",
        "Candidate_Id": "1542672061",
        "Count_Number": "5",
        "Firstname": "Andrea",
        "Surname": "McManus",
        "Candidate_First_Pref_Votes": "780.00",
        "Transfers": "67.00",
        "Total_Votes": "884.00",
        "Status": "Not Elected",
        "Occurred_On_Count": "10",
        "Party_Name": "Sinn Féin",
        "Deduplicated Party Name": "Sinn Féin",
        "Wikipedia Party Name": "Sinn Féin",
        "Party_Colour": "#326760",
        "candidateName": "Andrea McManus",
        "id": 64
      },
      {
        "Constituency_Number": "",
        "Candidate_Id": "1542672061",
        "Count_Number": "6",
        "Firstname": "Andrea",
        "Surname": "McManus",
        "Candidate_First_Pref_Votes": "780.00",
        "Transfers": "57.60",
        "Total_Votes": "941.00",
        "Status": "Not Elected",
        "Occurred_On_Count": "10",
        "Party_Name": "Sinn Féin",
        "Deduplicated Party Name": "Sinn Féin",
        "Wikipedia Party Name": "Sinn Féin",
        "Party_Colour": "#326760",
        "candidateName": "Andrea McManus",
        "id": 65
      },
      {
        "Constituency_Number": "",
        "Candidate_Id": "1542672061",
        "Count_Number": "7",
        "Firstname": "Andrea",
        "Surname": "McManus",
        "Candidate_First_Pref_Votes": "780.00",
        "Transfers": "20.37",
        "Total_Votes": "961.00",
        "Status": "Not Elected",
        "Occurred_On_Count": "10",
        "Party_Name": "Sinn Féin",
        "Deduplicated Party Name": "Sinn Féin",
        "Wikipedia Party Name": "Sinn Féin",
        "Party_Colour": "#326760",
        "candidateName": "Andrea McManus",
        "id": 66
      },
      {
        "Constituency_Number": "",
        "Candidate_Id": "1542672061",
        "Count_Number": "8",
        "Firstname": "Andrea",
        "Surname": "McManus",
        "Candidate_First_Pref_Votes": "780.00",
        "Transfers": "2.00",
        "Total_Votes": "963.00",
        "Status": "Not Elected",
        "Occurred_On_Count": "10",
        "Party_Name": "Sinn Féin",
        "Deduplicated Party Name": "Sinn Féin",
        "Wikipedia Party Name": "Sinn Féin",
        "Party_Colour": "#326760",
        "candidateName": "Andrea McManus",
        "id": 67
      },
      {
        "Constituency_Number": "",
        "Candidate_Id": "1542672061",
        "Count_Number": "9",
        "Firstname": "Andrea",
        "Surname": "McManus",
        "Candidate_First_Pref_Votes": "780.00",
        "Transfers": "0.00",
        "Total_Votes": "963.00",
        "Status": "Not Elected",
        "Occurred_On_Count": "10",
        "Party_Name": "Sinn Féin",
        "Deduplicated Party Name": "Sinn Féin",
        "Wikipedia Party Name": "Sinn Féin",
        "Party_Colour": "#326760",
        "candidateName": "Andrea McManus",
        "id": 68
      },
      {
        "Constituency_Number": "",
        "Candidate_Id": "1542672061",
        "Count_Number": "10",
        "Firstname": "Andrea",
        "Surname": "McManus",
        "Candidate_First_Pref_Votes": "780.00",
        "Transfers": "0.00",
        "Total_Votes": "963.00",
        "Status": "Not Elected",
        "Occurred_On_Count": "10",
        "Party_Name": "Sinn Féin",
        "Deduplicated Party Name": "Sinn Féin",
        "Wikipedia Party Name": "Sinn Féin",
        "Party_Colour": "#326760",
        "candidateName": "Andrea McManus",
        "id": 69
      },
      {
        "Constituency_Number": "",
        "Candidate_Id": "919779443",
        "Count_Number": "1",
        "Firstname": "Donald",
        "Surname": "Crawford",
        "Candidate_First_Pref_Votes": "509.00",
        "Transfers": "0.00",
        "Total_Votes": "509.00",
        "Status": "Excluded",
        "Occurred_On_Count": "10",
        "Party_Name": "TUV",
        "Deduplicated Party Name": "TUV",
        "Wikipedia Party Name": "TUV",
        "Party_Colour": "#0C3A6A",
        "candidateName": "Donald Crawford",
        "id": 70
      },
      {
        "Constituency_Number": "",
        "Candidate_Id": "919779443",
        "Count_Number": "2",
        "Firstname": "Donald",
        "Surname": "Crawford",
        "Candidate_First_Pref_Votes": "509.00",
        "Transfers": "22.00",
        "Total_Votes": "531.00",
        "Status": "Excluded",
        "Occurred_On_Count": "10",
        "Party_Name": "TUV",
        "Deduplicated Party Name": "TUV",
        "Wikipedia Party Name": "TUV",
        "Party_Colour": "#0C3A6A",
        "candidateName": "Donald Crawford",
        "id": 71
      },
      {
        "Constituency_Number": "",
        "Candidate_Id": "919779443",
        "Count_Number": "3",
        "Firstname": "Donald",
        "Surname": "Crawford",
        "Candidate_First_Pref_Votes": "509.00",
        "Transfers": "134.30",
        "Total_Votes": "665.00",
        "Status": "Excluded",
        "Occurred_On_Count": "10",
        "Party_Name": "TUV",
        "Deduplicated Party Name": "TUV",
        "Wikipedia Party Name": "TUV",
        "Party_Colour": "#0C3A6A",
        "candidateName": "Donald Crawford",
        "id": 72
      },
      {
        "Constituency_Number": "",
        "Candidate_Id": "919779443",
        "Count_Number": "4",
        "Firstname": "Donald",
        "Surname": "Crawford",
        "Candidate_First_Pref_Votes": "509.00",
        "Transfers": "3.00",
        "Total_Votes": "668.00",
        "Status": "Excluded",
        "Occurred_On_Count": "10",
        "Party_Name": "TUV",
        "Deduplicated Party Name": "TUV",
        "Wikipedia Party Name": "TUV",
        "Party_Colour": "#0C3A6A",
        "candidateName": "Donald Crawford",
        "id": 73
      },
      {
        "Constituency_Number": "",
        "Candidate_Id": "919779443",
        "Count_Number": "5",
        "Firstname": "Donald",
        "Surname": "Crawford",
        "Candidate_First_Pref_Votes": "509.00",
        "Transfers": "12.00",
        "Total_Votes": "680.00",
        "Status": "Excluded",
        "Occurred_On_Count": "10",
        "Party_Name": "TUV",
        "Deduplicated Party Name": "TUV",
        "Wikipedia Party Name": "TUV",
        "Party_Colour": "#0C3A6A",
        "candidateName": "Donald Crawford",
        "id": 74
      },
      {
        "Constituency_Number": "",
        "Candidate_Id": "919779443",
        "Count_Number": "6",
        "Firstname": "Donald",
        "Surname": "Crawford",
        "Candidate_First_Pref_Votes": "509.00",
        "Transfers": "2.88",
        "Total_Votes": "683.00",
        "Status": "Excluded",
        "Occurred_On_Count": "10",
        "Party_Name": "TUV",
        "Deduplicated Party Name": "TUV",
        "Wikipedia Party Name": "TUV",
        "Party_Colour": "#0C3A6A",
        "candidateName": "Donald Crawford",
        "id": 75
      },
      {
        "Constituency_Number": "",
        "Candidate_Id": "919779443",
        "Count_Number": "7",
        "Firstname": "Donald",
        "Surname": "Crawford",
        "Candidate_First_Pref_Votes": "509.00",
        "Transfers": "0.00",
        "Total_Votes": "683.00",
        "Status": "Excluded",
        "Occurred_On_Count": "10",
        "Party_Name": "TUV",
        "Deduplicated Party Name": "TUV",
        "Wikipedia Party Name": "TUV",
        "Party_Colour": "#0C3A6A",
        "candidateName": "Donald Crawford",
        "id": 76
      },
      {
        "Constituency_Number": "",
        "Candidate_Id": "919779443",
        "Count_Number": "8",
        "Firstname": "Donald",
        "Surname": "Crawford",
        "Candidate_First_Pref_Votes": "509.00",
        "Transfers": "-683.18",
        "Total_Votes": "0.00",
        "Status": "Excluded",
        "Occurred_On_Count": "10",
        "Party_Name": "TUV",
        "Deduplicated Party Name": "TUV",
        "Wikipedia Party Name": "TUV",
        "Party_Colour": "#0C3A6A",
        "candidateName": "Donald Crawford",
        "id": 77
      },
      {
        "Constituency_Number": "",
        "Candidate_Id": "919779443",
        "Count_Number": "9",
        "Firstname": "Donald",
        "Surname": "Crawford",
        "Candidate_First_Pref_Votes": "509.00",
        "Transfers": "0.00",
        "Total_Votes": "0.00",
        "Status": "Excluded",
        "Occurred_On_Count": "10",
        "Party_Name": "TUV",
        "Deduplicated Party Name": "TUV",
        "Wikipedia Party Name": "TUV",
        "Party_Colour": "#0C3A6A",
        "candidateName": "Donald Crawford",
        "id": 78
      },
      {
        "Constituency_Number": "",
        "Candidate_Id": "919779443",
        "Count_Number": "10",
        "Firstname": "Donald",
        "Surname": "Crawford",
        "Candidate_First_Pref_Votes": "509.00",
        "Transfers": "0.00",
        "Total_Votes": "0.00",
        "Status": "Excluded",
        "Occurred_On_Count": "10",
        "Party_Name": "TUV",
        "Deduplicated Party Name": "TUV",
        "Wikipedia Party Name": "TUV",
        "Party_Colour": "#0C3A6A",
        "candidateName": "Donald Crawford",
        "id": 79
      },
      {
        "Constituency_Number": "",
        "Candidate_Id": "2382922063",
        "Count_Number": "1",
        "Firstname": "Paul",
        "Surname": "Blake",
        "Candidate_First_Pref_Votes": "539.00",
        "Transfers": "0.00",
        "Total_Votes": "539.00",
        "Status": "Excluded",
        "Occurred_On_Count": "10",
        "Party_Name": "SDLP",
        "Deduplicated Party Name": "SDLP",
        "Wikipedia Party Name": "SDLP",
        "Party_Colour": "#2AA82C",
        "candidateName": "Paul Blake",
        "id": 80
      },
      {
        "Constituency_Number": "",
        "Candidate_Id": "2382922063",
        "Count_Number": "2",
        "Firstname": "Paul",
        "Surname": "Blake",
        "Candidate_First_Pref_Votes": "539.00",
        "Transfers": "0.00",
        "Total_Votes": "539.00",
        "Status": "Excluded",
        "Occurred_On_Count": "10",
        "Party_Name": "SDLP",
        "Deduplicated Party Name": "SDLP",
        "Wikipedia Party Name": "SDLP",
        "Party_Colour": "#2AA82C",
        "candidateName": "Paul Blake",
        "id": 81
      },
      {
        "Constituency_Number": "",
        "Candidate_Id": "2382922063",
        "Count_Number": "3",
        "Firstname": "Paul",
        "Surname": "Blake",
        "Candidate_First_Pref_Votes": "539.00",
        "Transfers": "0.00",
        "Total_Votes": "539.00",
        "Status": "Excluded",
        "Occurred_On_Count": "10",
        "Party_Name": "SDLP",
        "Deduplicated Party Name": "SDLP",
        "Wikipedia Party Name": "SDLP",
        "Party_Colour": "#2AA82C",
        "candidateName": "Paul Blake",
        "id": 82
      },
      {
        "Constituency_Number": "",
        "Candidate_Id": "2382922063",
        "Count_Number": "4",
        "Firstname": "Paul",
        "Surname": "Blake",
        "Candidate_First_Pref_Votes": "539.00",
        "Transfers": "124.00",
        "Total_Votes": "663.00",
        "Status": "Excluded",
        "Occurred_On_Count": "10",
        "Party_Name": "SDLP",
        "Deduplicated Party Name": "SDLP",
        "Wikipedia Party Name": "SDLP",
        "Party_Colour": "#2AA82C",
        "candidateName": "Paul Blake",
        "id": 83
      },
      {
        "Constituency_Number": "",
        "Candidate_Id": "2382922063",
        "Count_Number": "5",
        "Firstname": "Paul",
        "Surname": "Blake",
        "Candidate_First_Pref_Votes": "539.00",
        "Transfers": "-663.00",
        "Total_Votes": "0.00",
        "Status": "Excluded",
        "Occurred_On_Count": "10",
        "Party_Name": "SDLP",
        "Deduplicated Party Name": "SDLP",
        "Wikipedia Party Name": "SDLP",
        "Party_Colour": "#2AA82C",
        "candidateName": "Paul Blake",
        "id": 84
      },
      {
        "Constituency_Number": "",
        "Candidate_Id": "2382922063",
        "Count_Number": "6",
        "Firstname": "Paul",
        "Surname": "Blake",
        "Candidate_First_Pref_Votes": "539.00",
        "Transfers": "0.00",
        "Total_Votes": "0.00",
        "Status": "Excluded",
        "Occurred_On_Count": "10",
        "Party_Name": "SDLP",
        "Deduplicated Party Name": "SDLP",
        "Wikipedia Party Name": "SDLP",
        "Party_Colour": "#2AA82C",
        "candidateName": "Paul Blake",
        "id": 85
      },
      {
        "Constituency_Number": "",
        "Candidate_Id": "2382922063",
        "Count_Number": "7",
        "Firstname": "Paul",
        "Surname": "Blake",
        "Candidate_First_Pref_Votes": "539.00",
        "Transfers": "0.00",
        "Total_Votes": "0.00",
        "Status": "Excluded",
        "Occurred_On_Count": "10",
        "Party_Name": "SDLP",
        "Deduplicated Party Name": "SDLP",
        "Wikipedia Party Name": "SDLP",
        "Party_Colour": "#2AA82C",
        "candidateName": "Paul Blake",
        "id": 86
      },
      {
        "Constituency_Number": "",
        "Candidate_Id": "2382922063",
        "Count_Number": "8",
        "Firstname": "Paul",
        "Surname": "Blake",
        "Candidate_First_Pref_Votes": "539.00",
        "Transfers": "0.00",
        "Total_Votes": "0.00",
        "Status": "Excluded",
        "Occurred_On_Count": "10",
        "Party_Name": "SDLP",
        "Deduplicated Party Name": "SDLP",
        "Wikipedia Party Name": "SDLP",
        "Party_Colour": "#2AA82C",
        "candidateName": "Paul Blake",
        "id": 87
      },
      {
        "Constituency_Number": "",
        "Candidate_Id": "2382922063",
        "Count_Number": "9",
        "Firstname": "Paul",
        "Surname": "Blake",
        "Candidate_First_Pref_Votes": "539.00",
        "Transfers": "0.00",
        "Total_Votes": "0.00",
        "Status": "Excluded",
        "Occurred_On_Count": "10",
        "Party_Name": "SDLP",
        "Deduplicated Party Name": "SDLP",
        "Wikipedia Party Name": "SDLP",
        "Party_Colour": "#2AA82C",
        "candidateName": "Paul Blake",
        "id": 88
      },
      {
        "Constituency_Number": "",
        "Candidate_Id": "2382922063",
        "Count_Number": "10",
        "Firstname": "Paul",
        "Surname": "Blake",
        "Candidate_First_Pref_Votes": "539.00",
        "Transfers": "0.00",
        "Total_Votes": "0.00",
        "Status": "Excluded",
        "Occurred_On_Count": "10",
        "Party_Name": "SDLP",
        "Deduplicated Party Name": "SDLP",
        "Wikipedia Party Name": "SDLP",
        "Party_Colour": "#2AA82C",
        "candidateName": "Paul Blake",
        "id": 89
      },
      {
        "Constituency_Number": "",
        "Candidate_Id": "3685270777",
        "Count_Number": "1",
        "Firstname": "Donal",
        "Surname": "O'Cofaigh",
        "Candidate_First_Pref_Votes": "504.00",
        "Transfers": "0.00",
        "Total_Votes": "504.00",
        "Status": "Excluded",
        "Occurred_On_Count": "10",
        "Party_Name": "Cross-Community Labour Alternative",
        "Deduplicated Party Name": "Cross-Community Labour Alternative",
        "Wikipedia Party Name": "Cross-Community Labour Alternative",
        "Party_Colour": "#CD5C5C",
        "candidateName": "Donal O'Cofaigh",
        "id": 90
      },
      {
        "Constituency_Number": "",
        "Candidate_Id": "3685270777",
        "Count_Number": "2",
        "Firstname": "Donal",
        "Surname": "O'Cofaigh",
        "Candidate_First_Pref_Votes": "504.00",
        "Transfers": "2.00",
        "Total_Votes": "506.00",
        "Status": "Excluded",
        "Occurred_On_Count": "10",
        "Party_Name": "Cross-Community Labour Alternative",
        "Deduplicated Party Name": "Cross-Community Labour Alternative",
        "Wikipedia Party Name": "Cross-Community Labour Alternative",
        "Party_Colour": "#CD5C5C",
        "candidateName": "Donal O'Cofaigh",
        "id": 91
      },
      {
        "Constituency_Number": "",
        "Candidate_Id": "3685270777",
        "Count_Number": "3",
        "Firstname": "Donal",
        "Surname": "O'Cofaigh",
        "Candidate_First_Pref_Votes": "504.00",
        "Transfers": "1.70",
        "Total_Votes": "507.00",
        "Status": "Excluded",
        "Occurred_On_Count": "10",
        "Party_Name": "Cross-Community Labour Alternative",
        "Deduplicated Party Name": "Cross-Community Labour Alternative",
        "Wikipedia Party Name": "Cross-Community Labour Alternative",
        "Party_Colour": "#CD5C5C",
        "candidateName": "Donal O'Cofaigh",
        "id": 92
      },
      {
        "Constituency_Number": "",
        "Candidate_Id": "3685270777",
        "Count_Number": "4",
        "Firstname": "Donal",
        "Surname": "O'Cofaigh",
        "Candidate_First_Pref_Votes": "504.00",
        "Transfers": "-507.70",
        "Total_Votes": "0.00",
        "Status": "Excluded",
        "Occurred_On_Count": "10",
        "Party_Name": "Cross-Community Labour Alternative",
        "Deduplicated Party Name": "Cross-Community Labour Alternative",
        "Wikipedia Party Name": "Cross-Community Labour Alternative",
        "Party_Colour": "#CD5C5C",
        "candidateName": "Donal O'Cofaigh",
        "id": 93
      },
      {
        "Constituency_Number": "",
        "Candidate_Id": "3685270777",
        "Count_Number": "5",
        "Firstname": "Donal",
        "Surname": "O'Cofaigh",
        "Candidate_First_Pref_Votes": "504.00",
        "Transfers": "0.00",
        "Total_Votes": "0.00",
        "Status": "Excluded",
        "Occurred_On_Count": "10",
        "Party_Name": "Cross-Community Labour Alternative",
        "Deduplicated Party Name": "Cross-Community Labour Alternative",
        "Wikipedia Party Name": "Cross-Community Labour Alternative",
        "Party_Colour": "#CD5C5C",
        "candidateName": "Donal O'Cofaigh",
        "id": 94
      },
      {
        "Constituency_Number": "",
        "Candidate_Id": "3685270777",
        "Count_Number": "6",
        "Firstname": "Donal",
        "Surname": "O'Cofaigh",
        "Candidate_First_Pref_Votes": "504.00",
        "Transfers": "0.00",
        "Total_Votes": "0.00",
        "Status": "Excluded",
        "Occurred_On_Count": "10",
        "Party_Name": "Cross-Community Labour Alternative",
        "Deduplicated Party Name": "Cross-Community Labour Alternative",
        "Wikipedia Party Name": "Cross-Community Labour Alternative",
        "Party_Colour": "#CD5C5C",
        "candidateName": "Donal O'Cofaigh",
        "id": 95
      },
      {
        "Constituency_Number": "",
        "Candidate_Id": "3685270777",
        "Count_Number": "7",
        "Firstname": "Donal",
        "Surname": "O'Cofaigh",
        "Candidate_First_Pref_Votes": "504.00",
        "Transfers": "0.00",
        "Total_Votes": "0.00",
        "Status": "Excluded",
        "Occurred_On_Count": "10",
        "Party_Name": "Cross-Community Labour Alternative",
        "Deduplicated Party Name": "Cross-Community Labour Alternative",
        "Wikipedia Party Name": "Cross-Community Labour Alternative",
        "Party_Colour": "#CD5C5C",
        "candidateName": "Donal O'Cofaigh",
        "id": 96
      },
      {
        "Constituency_Number": "",
        "Candidate_Id": "3685270777",
        "Count_Number": "8",
        "Firstname": "Donal",
        "Surname": "O'Cofaigh",
        "Candidate_First_Pref_Votes": "504.00",
        "Transfers": "0.00",
        "Total_Votes": "0.00",
        "Status": "Excluded",
        "Occurred_On_Count": "10",
        "Party_Name": "Cross-Community Labour Alternative",
        "Deduplicated Party Name": "Cross-Community Labour Alternative",
        "Wikipedia Party Name": "Cross-Community Labour Alternative",
        "Party_Colour": "#CD5C5C",
        "candidateName": "Donal O'Cofaigh",
        "id": 97
      },
      {
        "Constituency_Number": "",
        "Candidate_Id": "3685270777",
        "Count_Number": "9",
        "Firstname": "Donal",
        "Surname": "O'Cofaigh",
        "Candidate_First_Pref_Votes": "504.00",
        "Transfers": "0.00",
        "Total_Votes": "0.00",
        "Status": "Excluded",
        "Occurred_On_Count": "10",
        "Party_Name": "Cross-Community Labour Alternative",
        "Deduplicated Party Name": "Cross-Community Labour Alternative",
        "Wikipedia Party Name": "Cross-Community Labour Alternative",
        "Party_Colour": "#CD5C5C",
        "candidateName": "Donal O'Cofaigh",
        "id": 98
      },
      {
        "Constituency_Number": "",
        "Candidate_Id": "3685270777",
        "Count_Number": "10",
        "Firstname": "Donal",
        "Surname": "O'Cofaigh",
        "Candidate_First_Pref_Votes": "504.00",
        "Transfers": "0.00",
        "Total_Votes": "0.00",
        "Status": "Excluded",
        "Occurred_On_Count": "10",
        "Party_Name": "Cross-Community Labour Alternative",
        "Deduplicated Party Name": "Cross-Community Labour Alternative",
        "Wikipedia Party Name": "Cross-Community Labour Alternative",
        "Party_Colour": "#CD5C5C",
        "candidateName": "Donal O'Cofaigh",
        "id": 99
      },
      {
        "Constituency_Number": "",
        "Candidate_Id": "907981068",
        "Count_Number": "1",
        "Firstname": "Jill",
        "Surname": "Mahon",
        "Candidate_First_Pref_Votes": "437.00",
        "Transfers": "0.00",
        "Total_Votes": "437.00",
        "Status": "Excluded",
        "Occurred_On_Count": "10",
        "Party_Name": "DUP",
        "Deduplicated Party Name": "DUP",
        "Wikipedia Party Name": "DUP",
        "Party_Colour": "#D46A4C",
        "candidateName": "Jill Mahon",
        "id": 100
      },
      {
        "Constituency_Number": "",
        "Candidate_Id": "907981068",
        "Count_Number": "2",
        "Firstname": "Jill",
        "Surname": "Mahon",
        "Candidate_First_Pref_Votes": "437.00",
        "Transfers": "-437.00",
        "Total_Votes": "0.00",
        "Status": "Excluded",
        "Occurred_On_Count": "10",
        "Party_Name": "DUP",
        "Deduplicated Party Name": "DUP",
        "Wikipedia Party Name": "DUP",
        "Party_Colour": "#D46A4C",
        "candidateName": "Jill Mahon",
        "id": 101
      },
      {
        "Constituency_Number": "",
        "Candidate_Id": "907981068",
        "Count_Number": "3",
        "Firstname": "Jill",
        "Surname": "Mahon",
        "Candidate_First_Pref_Votes": "437.00",
        "Transfers": "0.00",
        "Total_Votes": "0.00",
        "Status": "Excluded",
        "Occurred_On_Count": "10",
        "Party_Name": "DUP",
        "Deduplicated Party Name": "DUP",
        "Wikipedia Party Name": "DUP",
        "Party_Colour": "#D46A4C",
        "candidateName": "Jill Mahon",
        "id": 102
      },
      {
        "Constituency_Number": "",
        "Candidate_Id": "907981068",
        "Count_Number": "4",
        "Firstname": "Jill",
        "Surname": "Mahon",
        "Candidate_First_Pref_Votes": "437.00",
        "Transfers": "0.00",
        "Total_Votes": "0.00",
        "Status": "Excluded",
        "Occurred_On_Count": "10",
        "Party_Name": "DUP",
        "Deduplicated Party Name": "DUP",
        "Wikipedia Party Name": "DUP",
        "Party_Colour": "#D46A4C",
        "candidateName": "Jill Mahon",
        "id": 103
      },
      {
        "Constituency_Number": "",
        "Candidate_Id": "907981068",
        "Count_Number": "5",
        "Firstname": "Jill",
        "Surname": "Mahon",
        "Candidate_First_Pref_Votes": "437.00",
        "Transfers": "0.00",
        "Total_Votes": "0.00",
        "Status": "Excluded",
        "Occurred_On_Count": "10",
        "Party_Name": "DUP",
        "Deduplicated Party Name": "DUP",
        "Wikipedia Party Name": "DUP",
        "Party_Colour": "#D46A4C",
        "candidateName": "Jill Mahon",
        "id": 104
      },
      {
        "Constituency_Number": "",
        "Candidate_Id": "907981068",
        "Count_Number": "6",
        "Firstname": "Jill",
        "Surname": "Mahon",
        "Candidate_First_Pref_Votes": "437.00",
        "Transfers": "0.00",
        "Total_Votes": "0.00",
        "Status": "Excluded",
        "Occurred_On_Count": "10",
        "Party_Name": "DUP",
        "Deduplicated Party Name": "DUP",
        "Wikipedia Party Name": "DUP",
        "Party_Colour": "#D46A4C",
        "candidateName": "Jill Mahon",
        "id": 105
      },
      {
        "Constituency_Number": "",
        "Candidate_Id": "907981068",
        "Count_Number": "7",
        "Firstname": "Jill",
        "Surname": "Mahon",
        "Candidate_First_Pref_Votes": "437.00",
        "Transfers": "0.00",
        "Total_Votes": "0.00",
        "Status": "Excluded",
        "Occurred_On_Count": "10",
        "Party_Name": "DUP",
        "Deduplicated Party Name": "DUP",
        "Wikipedia Party Name": "DUP",
        "Party_Colour": "#D46A4C",
        "candidateName": "Jill Mahon",
        "id": 106
      },
      {
        "Constituency_Number": "",
        "Candidate_Id": "907981068",
        "Count_Number": "8",
        "Firstname": "Jill",
        "Surname": "Mahon",
        "Candidate_First_Pref_Votes": "437.00",
        "Transfers": "0.00",
        "Total_Votes": "0.00",
        "Status": "Excluded",
        "Occurred_On_Count": "10",
        "Party_Name": "DUP",
        "Deduplicated Party Name": "DUP",
        "Wikipedia Party Name": "DUP",
        "Party_Colour": "#D46A4C",
        "candidateName": "Jill Mahon",
        "id": 107
      },
      {
        "Constituency_Number": "",
        "Candidate_Id": "907981068",
        "Count_Number": "9",
        "Firstname": "Jill",
        "Surname": "Mahon",
        "Candidate_First_Pref_Votes": "437.00",
        "Transfers": "0.00",
        "Total_Votes": "0.00",
        "Status": "Excluded",
        "Occurred_On_Count": "10",
        "Party_Name": "DUP",
        "Deduplicated Party Name": "DUP",
        "Wikipedia Party Name": "DUP",
        "Party_Colour": "#D46A4C",
        "candidateName": "Jill Mahon",
        "id": 108
      },
      {
        "Constituency_Number": "",
        "Candidate_Id": "907981068",
        "Count_Number": "10",
        "Firstname": "Jill",
        "Surname": "Mahon",
        "Candidate_First_Pref_Votes": "437.00",
        "Transfers": "0.00",
        "Total_Votes": "0.00",
        "Status": "Excluded",
        "Occurred_On_Count": "10",
        "Party_Name": "DUP",
        "Deduplicated Party Name": "DUP",
        "Wikipedia Party Name": "DUP",
        "Party_Colour": "#D46A4C",
        "candidateName": "Jill Mahon",
        "id": 109
      },
      {
        "Constituency_Number": "",
        "Candidate_Id": "nontransferable",
        "Count_Number": "2",
        "Firstname": "Non-transferable",
        "Surname": "",
        "Candidate_First_Pref_Votes": "0.00",
        "Transfers": "1.00",
        "Total_Votes": "1.00",
        "Status": "",
        "Occurred_On_Count": "",
        "Party_Name": "Non-transferable",
        "Party_Colour": "#666666",
        "candidateName": "Non-transferable",
        "id": 110
      },
      {
        "Constituency_Number": "",
        "Candidate_Id": "nontransferable",
        "Count_Number": "3",
        "Firstname": "Non-transferable",
        "Surname": "",
        "Candidate_First_Pref_Votes": "0.00",
        "Transfers": "0.50",
        "Total_Votes": "1.50",
        "Status": "",
        "Occurred_On_Count": "",
        "Party_Name": "Non-transferable",
        "Party_Colour": "#666666",
        "candidateName": "Non-transferable",
        "id": 111
      },
      {
        "Constituency_Number": "",
        "Candidate_Id": "nontransferable",
        "Count_Number": "4",
        "Firstname": "Non-transferable",
        "Surname": "",
        "Candidate_First_Pref_Votes": "0.00",
        "Transfers": "54.70",
        "Total_Votes": "56.20",
        "Status": "",
        "Occurred_On_Count": "",
        "Party_Name": "Non-transferable",
        "Party_Colour": "#666666",
        "candidateName": "Non-transferable",
        "id": 112
      },
      {
        "Constituency_Number": "",
        "Candidate_Id": "nontransferable",
        "Count_Number": "5",
        "Firstname": "Non-transferable",
        "Surname": "",
        "Candidate_First_Pref_Votes": "0.00",
        "Transfers": "77.00",
        "Total_Votes": "133.20",
        "Status": "",
        "Occurred_On_Count": "",
        "Party_Name": "Non-transferable",
        "Party_Colour": "#666666",
        "candidateName": "Non-transferable",
        "id": 113
      },
      {
        "Constituency_Number": "",
        "Candidate_Id": "nontransferable",
        "Count_Number": "6",
        "Firstname": "Non-transferable",
        "Surname": "",
        "Candidate_First_Pref_Votes": "0.00",
        "Transfers": "0.48",
        "Total_Votes": "133.68",
        "Status": "",
        "Occurred_On_Count": "",
        "Party_Name": "Non-transferable",
        "Party_Colour": "#666666",
        "candidateName": "Non-transferable",
        "id": 114
      },
      {
        "Constituency_Number": "",
        "Candidate_Id": "nontransferable",
        "Count_Number": "7",
        "Firstname": "Non-transferable",
        "Surname": "",
        "Candidate_First_Pref_Votes": "0.00",
        "Transfers": "0.17",
        "Total_Votes": "133.85",
        "Status": "",
        "Occurred_On_Count": "",
        "Party_Name": "Non-transferable",
        "Party_Colour": "#666666",
        "candidateName": "Non-transferable",
        "id": 115
      },
      {
        "Constituency_Number": "",
        "Candidate_Id": "nontransferable",
        "Count_Number": "8",
        "Firstname": "Non-transferable",
        "Surname": "",
        "Candidate_First_Pref_Votes": "0.00",
        "Transfers": "84.26",
        "Total_Votes": "218.11",
        "Status": "",
        "Occurred_On_Count": "",
        "Party_Name": "Non-transferable",
        "Party_Colour": "#666666",
        "candidateName": "Non-transferable",
        "id": 116
      },
      {
        "Constituency_Number": "",
        "Candidate_Id": "nontransferable",
        "Count_Number": "9",
        "Firstname": "Non-transferable",
        "Surname": "",
        "Candidate_First_Pref_Votes": "0.00",
        "Transfers": "0.28",
        "Total_Votes": "218.39",
        "Status": "",
        "Occurred_On_Count": "",
        "Party_Name": "Non-transferable",
        "Party_Colour": "#666666",
        "candidateName": "Non-transferable",
        "id": 117
      }
    ]
  }
}