{
  "meta": {
    "quota": 6853
  },
  "candidates": [
    {
      "name": "Paddy Smith",
      "party": "Fianna Fail",
      "first_pref": 8172,
      "final_count": 1,
      "counts": [
        8172,
        1.19,
        0,
        1
      ],
      "status": ""
    },
    {
      "name": "John Tully",
      "party": "Clann na Poblachta",
      "first_pref": 6413,
      "final_count": 2,
      "counts": [
        6413,
        0.94,
        0,
        2
      ],
      "status": ""
    },
    {
      "name": "Michael Sheridan",
      "party": "Fianna Fail",
      "first_pref": 3564,
      "final_count": 3,
      "counts": [
        3564,
        0.52,
        0,
        3
      ],
      "status": ""
    },
    {
      "name": "Patrick O'Reilly",
      "party": "Fine Gael",
      "first_pref": 4911,
      "final_count": 4,
      "counts": [
        4911,
        0.72,
        0,
        4
      ],
      "status": ""
    },
    {
      "name": "John Cole",
      "party": "Non party/Independent",
      "first_pref": 4981,
      "final_count": 0,
      "counts": [
        4981,
        0.73,
        0
      ],
      "status": ""
    },
    {
      "name": "Patrick O'Reilly",
      "party": "Non party/Independent",
      "first_pref": 3438,
      "final_count": 0,
      "counts": [
        3438,
        0.5,
        0
      ],
      "status": ""
    },
    {
      "name": "Gerald Lovett",
      "party": "Fianna Fail",
      "first_pref": 2287,
      "final_count": 0,
      "counts": [
        2287,
        0.33,
        0
      ],
      "status": ""
    },
    {
      "name": "Eric O'Gowan",
      "party": "Non party/Independent",
      "first_pref": 495,
      "final_count": 0,
      "counts": [
        495,
        0.07,
        0
      ],
      "status": ""
    }
  ],
  "constituency": "Cavan",
  "year": 1951,
  "dail_num": 14,
  "cons_id": "36",
  "source_url": "https://electionsireland.org/result.cfm?election=1951&cons=36"
}