{
  "Constituency": {
    "countInfo": {
      "Constituency_Name": "Moyola",
      "Constituency_Number": "",
      "Number_Of_Seats": "5",
      "Quota": "1159",
      "Total_Electorate": "8583",
      "Total_Poll": "7104",
      "Valid_Poll": "6949",
      "Spoiled": "155"
    },
    "countGroup": [
      {
        "Constituency_Number": "",
        "Candidate_Id": "5595257340340429063",
        "Count_Number": "1",
        "Firstname": "Thomas James",
        "Surname": "Catherwood",
        "Candidate_First_Pref_Votes": "1023.00",
        "Party": "Democratic Unionist - DUP",
        "Elected": true
      },
      {
        "Constituency_Number": "",
        "Candidate_Id": "3780546304706975643",
        "Count_Number": "1",
        "Firstname": "Elizabeth Anne",
        "Surname": "Forde",
        "Candidate_First_Pref_Votes": "430.00",
        "Party": "Democratic Unionist - DUP",
        "Elected": false
      },
      {
        "Constituency_Number": "",
        "Candidate_Id": "3383063592715331020",
        "Count_Number": "1",
        "Firstname": "Elizabeth Mary Theresa (Betty)",
        "Surname": "Foster",
        "Candidate_First_Pref_Votes": "383.00",
        "Party": "SDLP",
        "Elected": false
      },
      {
        "Constituency_Number": "",
        "Candidate_Id": "7885456487813218570",
        "Count_Number": "1",
        "Firstname": "Oliver Thomas",
        "Surname": "Hughes",
        "Candidate_First_Pref_Votes": "1578.00",
        "Party": "Sinn Féin",
        "Elected": true
      },
      {
        "Constituency_Number": "",
        "Candidate_Id": "8218052593141665830",
        "Count_Number": "1",
        "Firstname": "Naaman",
        "Surname": "Hutchinson",
        "Candidate_First_Pref_Votes": "210.00",
        "Party": "Independent",
        "Elected": false
      },
      {
        "Constituency_Number": "",
        "Candidate_Id": "1443523397686608465",
        "Count_Number": "1",
        "Firstname": "John",
        "Surname": "Junkin",
        "Candidate_First_Pref_Votes": "1237.00",
        "Party": "Ulster Unionist Party",
        "Elected": true
      },
      {
        "Constituency_Number": "",
        "Candidate_Id": "7732690560007293056",
        "Count_Number": "1",
        "Firstname": "Patrick",
        "Surname": "McErlean",
        "Candidate_First_Pref_Votes": "713.00",
        "Party": "SDLP",
        "Elected": true
      },
      {
        "Constituency_Number": "",
        "Candidate_Id": "8626908920096199035",
        "Count_Number": "1",
        "Firstname": "James Patrick",
        "Surname": "O'Neill",
        "Candidate_First_Pref_Votes": "1375.00",
        "Party": "Sinn Féin",
        "Elected": true
      }
    ]
  }
}