{
  "Constituency": {
    "countInfo": {
      "Constituency_Name": "Kerry W",
      "Constituency_Number": "",
      "Number_Of_Seats": "1",
      "Spoiled": "",
      "Total_Electorate": "",
      "Total_Poll": "",
      "Valid_Poll": ""
    },
    "countGroup": [
      {
        "Candidate_First_Pref_Votes": "2,490",
        "Candidate_Id": "",
        "Constituency_Number": "",
        "Count_Number": "1",
        "Firstname": "Thomas",
        "Occurred_On_Count": "",
        "Party_Colour": "#0E7C42",
        "Party_Name": "Irish National Federation",
        "Status": "Elected",
        "Surname": "Esmonde",
        "Total_Votes": "2,490",
        "Transfers": "0.00",
        "candidateName": "Thomas Esmonde",
        "id": 0
      },
      {
        "Candidate_First_Pref_Votes": "1,143",
        "Candidate_Id": "",
        "Constituency_Number": "",
        "Count_Number": "1",
        "Firstname": "Edward",
        "Occurred_On_Count": "",
        "Party_Colour": "#0E7C42",
        "Party_Name": "Irish National League",
        "Status": "Not elected",
        "Surname": "Harrington",
        "Total_Votes": "1,143",
        "Transfers": "0.00",
        "candidateName": "Edward Harrington",
        "id": 1
      },
      {
        "Candidate_First_Pref_Votes": "43",
        "Candidate_Id": "",
        "Constituency_Number": "",
        "Count_Number": "1",
        "Firstname": "Richard Elliott",
        "Occurred_On_Count": "",
        "Party_Colour": "#0E7C42",
        "Party_Name": "Irish Unionist",
        "Status": "Not elected",
        "Surname": "Palmer",
        "Total_Votes": "43",
        "Transfers": "0.00",
        "candidateName": "Richard Elliott Palmer",
        "id": 2
      }
    ]
  }
}
