{
  "body": "Referendum (Ireland)",
  "constituency": "Longford–Roscommon",
  "topic": "14th Amendment — Information",
  "meta": {
    "electorate": 60452,
    "turnout_pct": 74.9,
    "spoiled": null
  },
  "yes": 16155,
  "no": 25701,
  "yes_pct": 38.6,
  "no_pct": 61.4,
  "outcome": "no",
  "counting_basis": "dail-constituencies",
  "source_url": "https://en.wikipedia.org/wiki/Fourteenth_Amendment_of_the_Constitution_of_Ireland",
  "candidates": [
    {
      "name": "Yes",
      "party": "Yes",
      "first_pref": 16155,
      "final_count": 1,
      "counts": [
        16155
      ],
      "status": "Not Elected"
    },
    {
      "name": "No",
      "party": "No",
      "first_pref": 25701,
      "final_count": 1,
      "counts": [
        25701
      ],
      "status": "Made Quota"
    }
  ]
}